coin_api/COIN_API.py
coin_api/__init__.py
coin_api-2.0.0.dist-info/METADATA
coin_api-2.0.0.dist-info/WHEEL
coin_api-2.0.0.dist-info/entry_points.txt
coin_api-2.0.0.dist-info/top_level.txt
coin_api-2.0.0.dist-info/RECORD
